[
  {
    "id": 1,
    "sentence": "The United Nations, in its first Digital Economy Report, states the US and China are leading the digital economy.",
    "tasks": [
      {
        "title": "主语",
        "indices": [2,4],
        "translation": "联合国"
      },
      {
        "title": "谓语",
        "indices": [20],
        "translation": "指出"
      },
      {
        "title": "宾从主语",
        "indices": [24,26,28],
        "translation": "美国和中国"
      },
      {
        "title": "宾从谓语",
        "indices": [30,32],
        "translation": "正在引领"
      },
      {
        "title": "宾从宾语",
        "indices": [36,38],
        "translation": "数字经济"
      },
      {
        "title": "插入语",
        "indices": [7,9,11,13,15,17],
        "translation": "在其首份《数字经济报告》中"
      }
    ],
    "fullTranslation": "联合国在其首份《数字经济报告》中指出，美国和中国正在引领数字经济。"
  }
]
